.gitignore
LICENSE.txt
README.rst
TODO.md
requirements.txt
setup.cfg
setup.py
get_media_files/__init__.py
get_media_files/__main__.py
get_media_files.egg-info/PKG-INFO
get_media_files.egg-info/SOURCES.txt
get_media_files.egg-info/dependency_links.txt
get_media_files.egg-info/entry_points.txt
get_media_files.egg-info/requires.txt
get_media_files.egg-info/top_level.txt
tests/__init__.py
tests/test_get_media_files.py
tests/media/044837513-two-women-walking-hill-1930s-v.jpg
tests/media/044838940-mountain-range-and-lake-2006-a.jpg
tests/media/045844231-my-mother.wav
tests/media/about.txt