Metadata-Version: 1.0
Name: get-media-files
Version: 0.2.0
Summary: Get info such as duration, type, or resolution of local files
Home-page: https://github.com/jtara1/get_media_files
Author: James T
Author-email: jtara@tuta.io
License: UNKNOWN
Platform: UNKNOWN
